cucumber_s/__init__.py
cucumber_s/library.py
cucumber_s-0.1.2.dist-info/METADATA
cucumber_s-0.1.2.dist-info/WHEEL
cucumber_s-0.1.2.dist-info/entry_points.txt
cucumber_s-0.1.2.dist-info/top_level.txt
cucumber_s-0.1.2.dist-info/RECORD
