Metadata-Version: 2.1
Name: cucumber_s
Version: 0.1.2
Summary: A Python library for creating various programs based on objectives
Home-page: https://github.com/yourusername/python_library
Author: Your Name
Author-email: your.email@example.com
Classifier: Programming Language :: Python :: 3
Classifier: License :: OSI Approved :: MIT License
Classifier: Operating System :: OS Independent
Requires-Python: >=3.6
